ineqpy/__init__.py
ineqpy/_statistics.py
ineqpy/_version.py
ineqpy/api.py
ineqpy/inequality.py
ineqpy/statistics.py
ineqpy/utils.py
ineqpy/grouped/__init__.py
ineqpy/grouped/inequality.py
ineqpy/grouped/stats.py
IneqPy-0.4.1.dist-info/METADATA
IneqPy-0.4.1.dist-info/WHEEL
IneqPy-0.4.1.dist-info/top_level.txt
IneqPy-0.4.1.dist-info/RECORD
