Metadata-Version: 2.1
Name: IneqPy
Version: 0.4.1
Summary: A Python Package To Quantitative Analysis Of Inequality
Home-page: https://github.com/mmngreco/IneqPy
Author: Maximiliano Greco
Author-email: mmngreco@gmail.com
Classifier: Development Status :: 3 - Alpha
Classifier: Intended Audience :: Science/Research
Classifier: License :: OSI Approved :: MIT License
Classifier: Programming Language :: Python :: 3
Classifier: Programming Language :: Python :: 3.6
Classifier: Programming Language :: Python :: 3.7
Classifier: Programming Language :: Python :: 3.8
Classifier: Programming Language :: Python :: 3.9
Classifier: Programming Language :: Python :: 3.10
Requires-Dist: numpy
Requires-Dist: pandas
Requires-Dist: numba
